trytond/modules/health_pediatrics_growth_charts/COPYING
trytond/modules/health_pediatrics_growth_charts/README.rst
trytond/modules/health_pediatrics_growth_charts/__init__.py
trytond/modules/health_pediatrics_growth_charts/health_pediatrics_growth_charts.py
trytond/modules/health_pediatrics_growth_charts/locale/ar.po
trytond/modules/health_pediatrics_growth_charts/locale/de.po
trytond/modules/health_pediatrics_growth_charts/locale/el.po
trytond/modules/health_pediatrics_growth_charts/locale/eo.po
trytond/modules/health_pediatrics_growth_charts/locale/es.po
trytond/modules/health_pediatrics_growth_charts/locale/fr.po
trytond/modules/health_pediatrics_growth_charts/locale/health_pediatrics_growth_charts.pot
trytond/modules/health_pediatrics_growth_charts/locale/it_IT.po
trytond/modules/health_pediatrics_growth_charts/locale/ja_JP.po
trytond/modules/health_pediatrics_growth_charts/locale/ka.po
trytond/modules/health_pediatrics_growth_charts/locale/lo.po
trytond/modules/health_pediatrics_growth_charts/locale/pt_BR.po
trytond/modules/health_pediatrics_growth_charts/locale/sv.po
trytond/modules/health_pediatrics_growth_charts/locale/tr.po
trytond/modules/health_pediatrics_growth_charts/locale/uk.po
trytond/modules/health_pediatrics_growth_charts/locale/zh_CN.po
trytond/modules/health_pediatrics_growth_charts/pyproject.toml
trytond/modules/health_pediatrics_growth_charts/tests/__init__.py
trytond/modules/health_pediatrics_growth_charts/tests/test_health_pediatrics_growth_charts.py
trytond/modules/health_pediatrics_growth_charts/tryton.cfg
gnuhealth_pediatrics_growth_charts-5.0.2.dist-info/METADATA
gnuhealth_pediatrics_growth_charts-5.0.2.dist-info/WHEEL
gnuhealth_pediatrics_growth_charts-5.0.2.dist-info/licenses/COPYING
gnuhealth_pediatrics_growth_charts-5.0.2.dist-info/RECORD
